{
	"archive" : {},
	"artifacts" : 
	[
		{
			"path" : "CGL/deps/glfw/src/libglfw3.a"
		}
	],
	"backtrace" : 1,
	"backtraceGraph" : 
	{
		"commands" : 
		[
			"add_library",
			"install",
			"add_definitions",
			"include_directories"
		],
		"files" : 
		[
			"CGL/deps/glfw/src/CMakeLists.txt"
		],
		"nodes" : 
		[
			{
				"file" : 0
			},
			{
				"command" : 0,
				"file" : 0,
				"line" : 60,
				"parent" : 0
			},
			{
				"command" : 1,
				"file" : 0,
				"line" : 94,
				"parent" : 0
			},
			{
				"command" : 2,
				"file" : 0,
				"line" : 6,
				"parent" : 0
			},
			{
				"command" : 3,
				"file" : 0,
				"line" : 2,
				"parent" : 0
			}
		]
	},
	"compileGroups" : 
	[
		{
			"compileCommandFragments" : 
			[
				{
					"fragment" : "-fPIC   -Wall"
				},
				{
					"fragment" : "-w"
				}
			],
			"defines" : 
			[
				{
					"backtrace" : 3,
					"define" : "_GLFW_USE_CONFIG_H"
				}
			],
			"includes" : 
			[
				{
					"backtrace" : 4,
					"path" : "/home/sheep/Learning/graphics/assignment8/CGL/deps/glfw/src"
				},
				{
					"backtrace" : 4,
					"path" : "/home/sheep/Learning/graphics/assignment8/build/CGL/deps/glfw/src"
				}
			],
			"language" : "C",
			"sourceIndexes" : 
			[
				0,
				1,
				2,
				3,
				4,
				5,
				6,
				7,
				8,
				9,
				10,
				11,
				12
			]
		}
	],
	"folder" : 
	{
		"name" : "GLFW3"
	},
	"id" : "glfw::@3a9041b068fa7b25e39f",
	"install" : 
	{
		"destinations" : 
		[
			{
				"backtrace" : 2,
				"path" : "lib"
			}
		],
		"prefix" : 
		{
			"path" : "/usr/local"
		}
	},
	"name" : "glfw",
	"nameOnDisk" : "libglfw3.a",
	"paths" : 
	{
		"build" : "CGL/deps/glfw/src",
		"source" : "CGL/deps/glfw/src"
	},
	"sourceGroups" : 
	[
		{
			"name" : "Source Files",
			"sourceIndexes" : 
			[
				0,
				1,
				2,
				3,
				4,
				5,
				6,
				7,
				8,
				9,
				10,
				11,
				12
			]
		},
		{
			"name" : "Header Files",
			"sourceIndexes" : 
			[
				13,
				14,
				15,
				16,
				17,
				18,
				19,
				20,
				21,
				22
			]
		}
	],
	"sources" : 
	[
		{
			"backtrace" : 1,
			"compileGroupIndex" : 0,
			"path" : "CGL/deps/glfw/src/context.c",
			"sourceGroupIndex" : 0
		},
		{
			"backtrace" : 1,
			"compileGroupIndex" : 0,
			"path" : "CGL/deps/glfw/src/init.c",
			"sourceGroupIndex" : 0
		},
		{
			"backtrace" : 1,
			"compileGroupIndex" : 0,
			"path" : "CGL/deps/glfw/src/input.c",
			"sourceGroupIndex" : 0
		},
		{
			"backtrace" : 1,
			"compileGroupIndex" : 0,
			"path" : "CGL/deps/glfw/src/monitor.c",
			"sourceGroupIndex" : 0
		},
		{
			"backtrace" : 1,
			"compileGroupIndex" : 0,
			"path" : "CGL/deps/glfw/src/window.c",
			"sourceGroupIndex" : 0
		},
		{
			"backtrace" : 1,
			"compileGroupIndex" : 0,
			"path" : "CGL/deps/glfw/src/x11_init.c",
			"sourceGroupIndex" : 0
		},
		{
			"backtrace" : 1,
			"compileGroupIndex" : 0,
			"path" : "CGL/deps/glfw/src/x11_monitor.c",
			"sourceGroupIndex" : 0
		},
		{
			"backtrace" : 1,
			"compileGroupIndex" : 0,
			"path" : "CGL/deps/glfw/src/x11_window.c",
			"sourceGroupIndex" : 0
		},
		{
			"backtrace" : 1,
			"compileGroupIndex" : 0,
			"path" : "CGL/deps/glfw/src/xkb_unicode.c",
			"sourceGroupIndex" : 0
		},
		{
			"backtrace" : 1,
			"compileGroupIndex" : 0,
			"path" : "CGL/deps/glfw/src/linux_joystick.c",
			"sourceGroupIndex" : 0
		},
		{
			"backtrace" : 1,
			"compileGroupIndex" : 0,
			"path" : "CGL/deps/glfw/src/posix_time.c",
			"sourceGroupIndex" : 0
		},
		{
			"backtrace" : 1,
			"compileGroupIndex" : 0,
			"path" : "CGL/deps/glfw/src/posix_tls.c",
			"sourceGroupIndex" : 0
		},
		{
			"backtrace" : 1,
			"compileGroupIndex" : 0,
			"path" : "CGL/deps/glfw/src/glx_context.c",
			"sourceGroupIndex" : 0
		},
		{
			"backtrace" : 1,
			"path" : "CGL/deps/glfw/src/internal.h",
			"sourceGroupIndex" : 1
		},
		{
			"backtrace" : 1,
			"path" : "build/CGL/deps/glfw/src/glfw_config.h",
			"sourceGroupIndex" : 1
		},
		{
			"backtrace" : 1,
			"path" : "CGL/deps/glfw/include/GLFW/glfw3.h",
			"sourceGroupIndex" : 1
		},
		{
			"backtrace" : 1,
			"path" : "CGL/deps/glfw/include/GLFW/glfw3native.h",
			"sourceGroupIndex" : 1
		},
		{
			"backtrace" : 1,
			"path" : "CGL/deps/glfw/src/x11_platform.h",
			"sourceGroupIndex" : 1
		},
		{
			"backtrace" : 1,
			"path" : "CGL/deps/glfw/src/xkb_unicode.h",
			"sourceGroupIndex" : 1
		},
		{
			"backtrace" : 1,
			"path" : "CGL/deps/glfw/src/linux_joystick.h",
			"sourceGroupIndex" : 1
		},
		{
			"backtrace" : 1,
			"path" : "CGL/deps/glfw/src/posix_time.h",
			"sourceGroupIndex" : 1
		},
		{
			"backtrace" : 1,
			"path" : "CGL/deps/glfw/src/posix_tls.h",
			"sourceGroupIndex" : 1
		},
		{
			"backtrace" : 1,
			"path" : "CGL/deps/glfw/src/glx_context.h",
			"sourceGroupIndex" : 1
		}
	],
	"type" : "STATIC_LIBRARY"
}
